{"course_id":"ANTH468P","neighbors":[{"id":"ANTH688P","score":0.8769,"title":"Current Developments in Anthropology; Anthropology, War & Security","dept":"Anthropology"},{"id":"ANTH469B","score":0.7596,"title":"Advanced Special Topics in Cultural Anthropology; Educational Anthropology","dept":"Anthropology"},{"id":"ANTH464","score":0.7097,"title":"Anthropology of Cultural Heritage","dept":"Anthropology"},{"id":"ANTH664","score":0.6719,"title":"Anthropology of Cultural Heritage","dept":"Anthropology"},{"id":"ANTH468F","score":0.6618,"title":"Special Topics in Cultural Anthropology; Introduction to American Indian Cultures of the U.S.","dept":"Anthropology"},{"id":"ANTH469C","score":0.6543,"title":"Advanced Special Topics in Cultural Anthropology; Language and Culture","dept":"Anthropology"},{"id":"ANTH688B","score":0.6523,"title":"Current Developments in Anthropology; Educational Anthropology","dept":"Anthropology"},{"id":"ANTH722","score":0.6489,"title":"Ecological Anthropology","dept":"Anthropology"},{"id":"ANTH469J","score":0.6455,"title":"Advanced Special Topics in Cultural Anthropology; Educational Anthropology","dept":"Anthropology"},{"id":"ANTH407","score":0.6246,"title":"Anthropology and Development","dept":"Anthropology"}]}