{"course_id":"ARCH478U","neighbors":[{"id":"ARCH678U","score":0.9676,"title":"Advanced Selected Topics in Architecture; The Black Experience & The American Built Environment","dept":"Architecture"},{"id":"ARCH468A","score":0.6839,"title":"Selected Topics in Architecture; Adaptive Reuse","dept":"Architecture"},{"id":"ARCH478M","score":0.6644,"title":"Selected Topics in Architecture; Origami Inspired, Self-assembling Clinic (OSAC) for Combating Coronavirus","dept":"Architecture"},{"id":"ARCH468K","score":0.6549,"title":"Selected Topics in Architecture; Entrpreneurship in Architecture","dept":"Architecture"},{"id":"ARCH468N","score":0.6549,"title":"Selected Topics in Architecture; Architecture and the Forest Aesthetic","dept":"Architecture"},{"id":"ARCH478L","score":0.6385,"title":"Selected Topics in Architecture; Architecture and Disaster Response in Historic Cities","dept":"Architecture"},{"id":"ARCH668A","score":0.6365,"title":"Advanced Selected Topics in Architecture; Adaptive Reuse","dept":"Architecture"},{"id":"ARCH678M","score":0.6365,"title":"Advanced Selected Topics in Architecture; Dwelling, Housing, House + Home","dept":"Architecture"},{"id":"ARCH668N","score":0.6326,"title":"Advanced Selected Topics in Architecture; Architecture and the Forest Aesthetic","dept":"Architecture"},{"id":"ARCH468P","score":0.6249,"title":"Selected Topics in Architecture; Resume and Portfolio Design","dept":"Architecture"}]}