{"course_id":"BMGT198B","neighbors":[{"id":"BMGT758L","score":0.9384,"title":"Special Topics in Business and Management; Corporate Venturing","dept":"Business and Management"},{"id":"BMGT758K","score":0.8712,"title":"Special Topics in Business and Management; Organizational Change","dept":"Business and Management"},{"id":"BMGT758A","score":0.846,"title":"Special Topics in Business and Management; AI and Business Strategy","dept":"Business and Management"},{"id":"BUSO758X","score":0.8378,"title":"Special Topics in Business; Digital Promotion and Advertising","dept":"Online MBA Program"},{"id":"BUSI718B","score":0.8197,"title":"Special Topics in Business; International Business","dept":"Part-Time MBA Program"},{"id":"BUSO758F","score":0.7973,"title":"Special Topics in Business; Platform Strategy and Transformation","dept":"Online MBA Program"},{"id":"BMGT758P","score":0.7927,"title":"Special Topics in Business and Management; Sustainability: Economics and Strategy","dept":"Business and Management"},{"id":"BMGT758F","score":0.7743,"title":"Special Topics in Business and Management; Market Forecasting","dept":"Business and Management"},{"id":"BMGT498L","score":0.7743,"title":"Special Topics in Business and Management","dept":"Business and Management"},{"id":"BUSI758W","score":0.7678,"title":"Special Topics in Business; Systems and Design Thinking","dept":"Part-Time MBA Program"}]}