{"course_id":"BSST389","neighbors":[{"id":"BSST386","score":0.9249,"title":"Experiential Learning in Terrorism Studies","dept":"Terrorism Studies"},{"id":"BSST330","score":0.7166,"title":"Terrorism Studies","dept":"Terrorism Studies"},{"id":"BSST200","score":0.7166,"title":"Terrorism Studies","dept":"Terrorism Studies"},{"id":"BSST698B","score":0.6741,"title":"Seminar in Terrorism Studies; Ethics of Terrorism Studies","dept":"Terrorism Studies"},{"id":"BSST631","score":0.6569,"title":"Societal Impacts of and Responses to Terrorism","dept":"Terrorism Studies"},{"id":"BSST640","score":0.6551,"title":"Theories of Security and Terrorism Studies","dept":"Terrorism Studies"},{"id":"BSST638F","score":0.6499,"title":"Special Topics in Terrorism Studies; Financing Terror and Hate","dept":"Terrorism Studies"},{"id":"BSST638B","score":0.6499,"title":"Special Topics in Terrorism Studies; Terrorist Hostage Taking","dept":"Terrorism Studies"},{"id":"BSST399F","score":0.6484,"title":"Individual Study in Terrorism Studies; Geospatial Analysis of Terrorism","dept":"Terrorism Studies"},{"id":"BSST338D","score":0.6394,"title":"Special Topics in Terrorism Studies; Psychology of Radicalization and Terrorism","dept":"Terrorism Studies"}]}