{"course_id":"BSST644","neighbors":[{"id":"GVPT406H","score":0.4614,"title":"International Organizations","dept":"Government and Politics"},{"id":"GVPT406","score":0.4614,"title":"International Organizations","dept":"Government and Politics"},{"id":"CHEM648G","score":0.3784,"title":"Special Topics in Organic Chemistry; Introduction to Chemical Biology","dept":"Chemistry"},{"id":"GVPT319E","score":0.3764,"title":"Topics in Social Advocacy; Careers in International Relations","dept":"Government and Politics"},{"id":"CHEM684","score":0.3672,"title":"Chemical Thermodynamics","dept":"Chemistry"},{"id":"CHEM316","score":0.3672,"title":"Chemical Demonstrations and Outreach","dept":"Chemistry"},{"id":"ENMA680","score":0.3656,"title":"Determination of Structure, Chemical Composition and Defects in Materials","dept":"Engineering, Materials"},{"id":"BCHM676","score":0.3407,"title":"Biological Mass Spectrometry","dept":"Biochemistry"},{"id":"BIOE689B","score":0.3373,"title":"Special Topics in Bioengineering; Engineered Living Materials","dept":"Bioengineering"},{"id":"PLCY388R","score":0.333,"title":"Special Topics in Public Policy; Nuclear Security Policy","dept":"Public Policy"}]}