{"course_id":"CMSC388R","neighbors":[{"id":"CMSC388W","score":0.7253,"title":"Special Topics in Computer Science; Usability of Programming Languages","dept":"Computer Science"},{"id":"CMSC389B","score":0.6988,"title":"Special Topics in Computer Science; A Tour of Programming Languages","dept":"Computer Science"},{"id":"CMSC388V","score":0.6984,"title":"Special Topics in Computer Science; A Modular Approach to Audio Programming","dept":"Computer Science"},{"id":"CMSC388Q","score":0.6768,"title":"Special Topics in Computer Science; Functional Programming in Racket","dept":"Computer Science"},{"id":"CMSC388X","score":0.6767,"title":"Special Topics in Computer Science; Introduction to Programming Language Theory","dept":"Computer Science"},{"id":"CMSC388Z","score":0.6261,"title":"Special Topics in Computer Science; Programming in Rust","dept":"Computer Science"},{"id":"CMSC398B","score":0.6182,"title":"Special Topics in Computer Science; Introduction to Go","dept":"Computer Science"},{"id":"CMSC389R","score":0.6005,"title":"Special Topics in Computer Science; Introduction to Ethical Hacking","dept":"Computer Science"},{"id":"CMSC389E","score":0.5608,"title":"Special Topics in Computer Science; Digital Logic Design Through Minecraft","dept":"Computer Science"},{"id":"CMSC398U","score":0.5581,"title":"Special Topics in Computer Science; Secure Multiparty Computation","dept":"Computer Science"}]}