{"course_id":"COMM425","neighbors":[{"id":"BMSO754","score":0.8211,"title":"Negotiation and Conflict Management","dept":"Online Business MS Programs"},{"id":"GFPL388B","score":0.782,"title":"Special Topics in Global and Foreign Policy; Conflict and Peace Processes","dept":"Global and Foreign Policy"},{"id":"GVPT409A","score":0.7694,"title":"Seminar in International Relations and World Politics; Peace and Conflict Processes","dept":"Government and Politics"},{"id":"GVPT413","score":0.7305,"title":"Conflict and Peace Processes","dept":"Government and Politics"},{"id":"COMM426","score":0.6969,"title":"Conflict Management","dept":"Communication"},{"id":"GVPT409J","score":0.6653,"title":"Seminar in International Relations and World Politics; Youth and Conflict","dept":"Government and Politics"},{"id":"MLAW358Q","score":0.6633,"title":"Selected Topics in Law and Society; Conflict in the International System","dept":"MPower Undergraduate Law Programs"},{"id":"ISRL349V","score":0.6536,"title":"Investigating Topics in Israel Studies; The Arab-Israeli Conflict Through Film","dept":"Israel Studies"},{"id":"GVPT409P","score":0.6534,"title":"Seminar in International Relations and World Politics; Conflict in the International System","dept":"Government and Politics"},{"id":"PLCY752","score":0.6515,"title":"Managing Differences:Resolving Conflict and Negotiating Agreements","dept":"Public Policy"}]}