{"course_id":"COMM619P","neighbors":[{"id":"RUSS405","score":0.9587,"title":"Russian-English Translation I","dept":"Russian"},{"id":"COMM619O","score":0.9566,"title":"Consecutive Interpretation; English into Russian/Russian into English","dept":"Communication"},{"id":"COMM629N","score":0.9307,"title":"Introduction to Simultaneous Interpretation; English into Russian/Russian into English","dept":"Communication"},{"id":"RUSS398P","score":0.7271,"title":"Selected Topics in Russian Language and Literature; Russian Culture under Putin: Power, Protest, and War","dept":"Russian"},{"id":"COMM719D","score":0.7027,"title":"Advanced Consecutive Interpretation; Russian into English/English into Russian","dept":"Communication"},{"id":"COMM749D","score":0.7027,"title":"Advanced Simultaneous Interpretation; Russian into English/English into Russian","dept":"Communication"},{"id":"HIST237","score":0.6994,"title":"Russian Civilization","dept":"History"},{"id":"COMM729R","score":0.697,"title":"Simultaneous Interpretation; Russian into English/English into Russian","dept":"Communication"},{"id":"COMM719R","score":0.6912,"title":"Advanced Consecutive Interpretation; Russian into English/English into Russian","dept":"Communication"},{"id":"COMM609O","score":0.6654,"title":"Fundamentals of Interpreting; English into Russian/Russian into English","dept":"Communication"}]}