{"course_id":"DANC489D","neighbors":[{"id":"DANC489X","score":1.0,"title":"Special Topics in Dance; TBA","dept":"Dance"},{"id":"DANC489R","score":0.9609,"title":"Special Topics in Dance; Researching Dance","dept":"Dance"},{"id":"DANC689V","score":0.9102,"title":"Special Topics in Dance; Global Dance Repertory","dept":"Dance"},{"id":"DANC689E","score":0.8569,"title":"Special Topics in Dance; Dance Pedagogy - Dance History","dept":"Dance"},{"id":"DANC689A","score":0.856,"title":"Special Topics in Dance; The Art of the Duet","dept":"Dance"},{"id":"DANC689M","score":0.8178,"title":"Special Topics in Dance; Dance Pedagogy - Modern Technique","dept":"Dance"},{"id":"DANC468","score":0.8068,"title":"Dance Repertory","dept":"Dance"},{"id":"DANC689O","score":0.8025,"title":"Special Topics in Dance; Dance Pedagogy - Movement Integration","dept":"Dance"},{"id":"DANC689W","score":0.7878,"title":"Special Topics in Dance; Choreography for Theatre","dept":"Dance"},{"id":"DANC489I","score":0.7807,"title":"Special Topics in Dance; Intro to Improvisational Techniques","dept":"Dance"}]}