{"course_id":"DANC489R","neighbors":[{"id":"DANC489X","score":0.9609,"title":"Special Topics in Dance; TBA","dept":"Dance"},{"id":"DANC489D","score":0.9609,"title":"Special Topics in Dance; Screendance","dept":"Dance"},{"id":"DANC689V","score":0.9472,"title":"Special Topics in Dance; Global Dance Repertory","dept":"Dance"},{"id":"DANC468","score":0.9389,"title":"Dance Repertory","dept":"Dance"},{"id":"DANC689E","score":0.9222,"title":"Special Topics in Dance; Dance Pedagogy - Dance History","dept":"Dance"},{"id":"DANC138G","score":0.8784,"title":"Global Dance Forms; Improvisation in Dance","dept":"Dance"},{"id":"DANC138Z","score":0.8784,"title":"Global Dance Forms; Disco Dance","dept":"Dance"},{"id":"DANC689M","score":0.8513,"title":"Special Topics in Dance; Dance Pedagogy - Modern Technique","dept":"Dance"},{"id":"DANC489I","score":0.8398,"title":"Special Topics in Dance; Intro to Improvisational Techniques","dept":"Dance"},{"id":"DANC689O","score":0.8358,"title":"Special Topics in Dance; Dance Pedagogy - Movement Integration","dept":"Dance"}]}