{"course_id":"EDHI667","neighbors":[{"id":"HESI707","score":0.9522,"title":"Women and Gender in Higher Education","dept":"Higher Ed, Student Affairs, and International Ed Policy"},{"id":"CHSE601","score":0.8931,"title":"Difficult Dialogues in Higher Education","dept":"Counseling, Higher Education, and Special Education"},{"id":"AAPS380","score":0.8288,"title":"Fearless First: Negotiating the Hidden Curriculum in Higher Education and Other Societal Institutions","dept":"Academic Achievement Programs"},{"id":"EDHI662","score":0.8153,"title":"Research on Ethnic Minorities and Demographic Trends in Higher Education","dept":"Education Leadership, Higher Ed and International Ed"},{"id":"EDHI677","score":0.8103,"title":"Ranking System in Higher Education: How They Work and Why They Matter","dept":"Education Leadership, Higher Ed and International Ed"},{"id":"EDHI750","score":0.8063,"title":"International Higher Education","dept":"Education Leadership, Higher Ed and International Ed"},{"id":"EDHI853","score":0.7903,"title":"Leadership in Higher Education","dept":"Education Leadership, Higher Ed and International Ed"},{"id":"EDHI754","score":0.7686,"title":"Higher Education Finance","dept":"Education Leadership, Higher Ed and International Ed"},{"id":"EDHI652","score":0.7632,"title":"Higher Education in American Society","dept":"Education Leadership, Higher Ed and International Ed"},{"id":"EDCP775","score":0.7576,"title":"Facilitating Student Learning in Higher Education","dept":"Education Counseling and Personnel Services"}]}