{"course_id":"EDSP426","neighbors":[{"id":"GEOG385","score":0.8798,"title":"Internship in Geography II","dept":"Geographical Sciences"},{"id":"GEOG385H","score":0.8798,"title":"Internship in Geography II","dept":"Geographical Sciences"},{"id":"EDSP425","score":0.8069,"title":"Pre-Internship I","dept":"Education, Special"},{"id":"BSCI288H","score":0.7142,"title":"Internship","dept":"Biological Sciences Program"},{"id":"ENST389","score":0.7142,"title":"Internship","dept":"Environmental Science and Technology"},{"id":"EDHD432","score":0.7142,"title":"Internship in EC/ECSE","dept":"Education, Human Development"},{"id":"INAG288","score":0.7142,"title":"Internship","dept":"Institute of Applied Agriculture"},{"id":"ANTH789","score":0.7142,"title":"Internship","dept":"Anthropology"},{"id":"CHSE489","score":0.7142,"title":"Internship - Terps Exceed","dept":"Counseling, Higher Education, and Special Education"},{"id":"ENSP386","score":0.7142,"title":"Internship","dept":"Environmental Science and Policy"}]}