{"course_id":"ENCE676","neighbors":[{"id":"ECON402","score":0.7048,"title":"Macroeconomic Models and Forecasting","dept":"Economics"},{"id":"SURV730","score":0.7048,"title":"Measurement Error Models","dept":"Survey Methodology"},{"id":"STAT422","score":0.6706,"title":"Probability Models","dept":"Statistics and Probability"},{"id":"STAT740","score":0.6342,"title":"Linear Statistical Models I","dept":"Statistics and Probability"},{"id":"EPIB741","score":0.5753,"title":"Association Models for Cohort and Cross-Sectional Studies","dept":"Epidemiology and Biostatistics"},{"id":"BUDT731","score":0.5747,"title":"Data, Models, and Decisions Using R","dept":"Decision and Information Technologies"},{"id":"STAT498J","score":0.572,"title":"Selected Topics in Statistics; Probability Models","dept":"Statistics and Probability"},{"id":"ENCE689X","score":0.5666,"title":"Seminar; Statistical and Machine Learning Models for Natural Hazards Prediction","dept":"Engineering, Civil"},{"id":"STAT741","score":0.5659,"title":"Linear Statistical Models II","dept":"Statistics and Probability"},{"id":"BMSO600","score":0.5575,"title":"Data, Models and Decisions","dept":"Online Business MS Programs"}]}