{"course_id":"ENCE205","neighbors":[{"id":"BSCI279E","score":0.6922,"title":"Supplemental Study; Environmental Biology","dept":"Biological Sciences Program"},{"id":"ENCE465","score":0.638,"title":"Civil and Environmental Engineering Design I","dept":"Engineering, Civil"},{"id":"ENCE202","score":0.638,"title":"Engineering Drawings and Design for Civil and Environmental Engineers","dept":"Engineering, Civil"},{"id":"ENCE467","score":0.572,"title":"Civil and Environmental Engineering Design II","dept":"Engineering, Civil"},{"id":"ENBC353","score":0.571,"title":"Synthetic Biology","dept":"Biocomputational Engineering"},{"id":"BSCI430","score":0.571,"title":"Developmental Biology","dept":"Biological Sciences Program"},{"id":"BSCI467","score":0.571,"title":"Freshwater Biology","dept":"Biological Sciences Program"},{"id":"BIOE120","score":0.571,"title":"Biology for Engineers","dept":"Bioengineering"},{"id":"BSCI337","score":0.571,"title":"Biology of Insects","dept":"Biological Sciences Program"},{"id":"BSCI363","score":0.571,"title":"The Biology of Conservation and Extinction","dept":"Biological Sciences Program"}]}