{"course_id":"ENES150","neighbors":[{"id":"HESP498C","score":1.0,"title":"Seminar; Cochlear Implants","dept":"Hearing and Speech Sciences"},{"id":"COMM655","score":1.0,"title":"Seminar in Speechwriting","dept":"Communication"},{"id":"ENES214","score":1.0,"title":"Virtus Seminar IV","dept":"Engineering Science"},{"id":"LING879D","score":1.0,"title":"Seminar in Semantics","dept":"Linguistics"},{"id":"LING879E","score":1.0,"title":"Seminar in Semantics","dept":"Linguistics"},{"id":"LING879G","score":1.0,"title":"Seminar in Semantics","dept":"Linguistics"},{"id":"LING879A","score":1.0,"title":"Seminar in Semantics","dept":"Linguistics"},{"id":"LING879O","score":1.0,"title":"Seminar in Semantics","dept":"Linguistics"},{"id":"BCHM889C","score":1.0,"title":"Seminar; Allostery in DNA Binding","dept":"Biochemistry"},{"id":"BCHM889D","score":1.0,"title":"Seminar; Enzymology Recombination","dept":"Biochemistry"}]}