{"course_id":"ENGL472","neighbors":[{"id":"ENGL471","score":0.9357,"title":"African-American Literature: 1910-1945","dept":"English"},{"id":"ENGL470","score":0.9321,"title":"African-American Literature: From Slavery to Freedom","dept":"English"},{"id":"AASP478K","score":0.8363,"title":"Humanities Topics in African American Studies; African-American Literature: 1945 to Present","dept":"African American Studies"},{"id":"AASP478B","score":0.8265,"title":"Humanities Topics in African American Studies; African-American Literature: From Slavery to Freedom","dept":"African American Studies"},{"id":"ENGL368I","score":0.8055,"title":"Special Topics in African American, African, and African Diaspora Literatures; Representing Black Soldiers in American Literature","dept":"English"},{"id":"ENGL628F","score":0.7934,"title":"Readings in African American Literature; Race, Decoloniality, and the Afterlives of Slavery","dept":"English"},{"id":"ENGL628G","score":0.785,"title":"Readings in African American Literature; Comparative Black and Native American Literature","dept":"English"},{"id":"ENGL628E","score":0.7827,"title":"Readings in African American Literature; Exploring Imagined Black Worlds","dept":"English"},{"id":"AASP478N","score":0.7811,"title":"Humanities Topics in African American Studies; African-American Literature: 1910-1945","dept":"African American Studies"},{"id":"ENGL368D","score":0.781,"title":"Special Topics in African American, African, and African Diaspora Literatures; African American Folklore and Literature","dept":"English"}]}