{"course_id":"ENGL348G","neighbors":[{"id":"ENTS689F","score":0.5137,"title":"Special Topics in Telecommunications; Fundamental of Wireless LANs","dept":"Telecommunications"},{"id":"WGSS348B","score":0.4967,"title":"Literary Works by Women; American Autobiographics","dept":"Women, Gender, and Sexuality Studies"},{"id":"ENGL404","score":0.4847,"title":"Shakespeare: The Later Works","dept":"English"},{"id":"ENEE698E","score":0.4807,"title":"Graduate Seminar; Microelectronics","dept":"Electrical & Computer Engineering"},{"id":"ENTS749E","score":0.4586,"title":"Advanced Topics in Networking; Network Automation","dept":"Telecommunications"},{"id":"ENTS629A","score":0.4518,"title":"Special Topics in Cybersecurity; System Security","dept":"Telecommunications"},{"id":"ENGL348B","score":0.4495,"title":"Literary Works by Women; Haunted Histories: Contemporary African American Gothic","dept":"English"},{"id":"ENTS689N","score":0.4429,"title":"Special Topics in Telecommunications; Network Programming","dept":"Telecommunications"},{"id":"FREN699Q","score":0.4359,"title":"Seminar; From the Surreal to the Real: Studies of French Fiction of the 20th and 21st Centuries","dept":"French"},{"id":"ENGL438C","score":0.4335,"title":"Selected Topics in Media Studies; Graphic Novels by People of Color","dept":"English"}]}