{"course_id":"ENGL274","neighbors":[{"id":"AASP274","score":1.0,"title":"Creative Writing Through The Eyes of African Americans: A Beginning Workshop","dept":"African American Studies"},{"id":"ENGL275","score":0.6866,"title":"Writing for the Stage and Screen: An Introductory Workshop","dept":"English"},{"id":"ARHU275","score":0.6866,"title":"Writing for the Stage and Screen: An Introductory Workshop","dept":"Arts and Humanities"},{"id":"KNES628","score":0.6089,"title":"PCS Research & Writing Workshop","dept":"Kinesiology"},{"id":"HONR238P","score":0.5584,"title":"Honors Seminar; Memory, Imagination, Invention: A Creative Writing Workshop","dept":"Honors"},{"id":"ARHU298J","score":0.5575,"title":"Special Problems in Arts and Humanities; Creative Writing Workshop","dept":"Arts and Humanities"},{"id":"ECON828","score":0.5434,"title":"Workshop in Econometrics","dept":"Economics"},{"id":"MUSC379","score":0.5434,"title":"Opera Workshop","dept":"School of Music"},{"id":"ENGL273","score":0.5277,"title":"Writing Poetry: An Introductory Workshop","dept":"English"},{"id":"ENGL688","score":0.5203,"title":"Poetry Workshop","dept":"English"}]}