{"course_id":"ENME808E","neighbors":[{"id":"ENME808N","score":0.7325,"title":"Advanced Topics in Mechanical Engineering","dept":"Engineering, Mechanical"},{"id":"ENME808","score":0.7325,"title":"Advanced Topics in Mechanical Engineering","dept":"Engineering, Mechanical"},{"id":"ENME299Z","score":0.7266,"title":"Topics in Mechanical Engineering; The Legend of Zelda: A Link to Machine Design","dept":"Engineering, Mechanical"},{"id":"ENME289Z","score":0.7219,"title":"Exploring Topics in Mechanical Engineering; The Legend of Zelda: A Link to Machine Design","dept":"Engineering, Mechanical"},{"id":"ENME808J","score":0.6931,"title":"Advanced Topics in Mechanical Engineering; Cost Analysis for Engineers","dept":"Engineering, Mechanical"},{"id":"ENME808D","score":0.6889,"title":"Advanced Topics in Mechanical Engineering; Thermal Management of Electronics","dept":"Engineering, Mechanical"},{"id":"ENME808L","score":0.6629,"title":"Advanced Topics in Mechanical Engineering; Control of Mobile Robots","dept":"Engineering, Mechanical"},{"id":"ENME808A","score":0.6627,"title":"Advanced Topics in Mechanical Engineering; Batteries: Operation, Modeling, and Reliability","dept":"Engineering, Mechanical"},{"id":"ENPM808A","score":0.6626,"title":"Advanced Topics in Engineering; Introduction to Machine Learning","dept":"Engineering, Professional Masters"},{"id":"ENME808C","score":0.6589,"title":"Advanced Topics in Mechanical Engineering; Renewable Energy","dept":"Engineering, Mechanical"}]}