{"course_id":"ENME645","neighbors":[{"id":"ENME809C","score":0.8467,"title":"Special Topics; Fluid Structure Interactions","dept":"Engineering, Mechanical"},{"id":"BCHM889P","score":0.7648,"title":"Seminar; Structure and Reactivity of Biopolymers","dept":"Biochemistry"},{"id":"LING419K","score":0.7446,"title":"Topics in Syntax; Studies in Lexical Aspect and Event Structure","dept":"Linguistics"},{"id":"ASTR606","score":0.701,"title":"Stellar Structure and Evolution","dept":"Astronomy"},{"id":"ASTR406","score":0.701,"title":"Stellar Structure and Evolution","dept":"Astronomy"},{"id":"LING659M","score":0.6962,"title":"Structure of a Language","dept":"Linguistics"},{"id":"ENTM788J","score":0.6798,"title":"Entomological Topics; Arthropod Structure, Function & Evolution","dept":"Entomology"},{"id":"ENMA650","score":0.6541,"title":"Nanometer Structure of Materials","dept":"Engineering, Materials"},{"id":"LING625","score":0.6472,"title":"Morphology and the Lexicon","dept":"Linguistics"},{"id":"CHEM460","score":0.6365,"title":"Structure Determination Using Spectroscopic Methods","dept":"Chemistry"}]}