{"course_id":"ENTM699K","neighbors":[{"id":"BIOL608K","score":0.9121,"title":"Biology Seminar; Biological Sciences Teaching and Learning in Higher Education","dept":"Biology"},{"id":"CBMG699K","score":0.679,"title":"Special Problems in Cell Biology and Molecular Genetics; Biological Sciences Teaching and Learning in Higher Education","dept":"Cell Biology & Molecular Genetics"},{"id":"TLPL623","score":0.642,"title":"Learning and Teaching Biological Sciences","dept":"Teaching and Learning, Policy and Leadership"},{"id":"SLLC601","score":0.6412,"title":"Teaching Foreign Languages in Higher Education","dept":"School of Languages, Literatures and Cultures"},{"id":"CHSE601","score":0.6377,"title":"Difficult Dialogues in Higher Education","dept":"Counseling, Higher Education, and Special Education"},{"id":"EDCP775","score":0.6273,"title":"Facilitating Student Learning in Higher Education","dept":"Education Counseling and Personnel Services"},{"id":"CHEM608K","score":0.6122,"title":"Selected Topics in Inorganic Chemistry; Chemistry Teaching and Learning in Higher Education","dept":"Chemistry"},{"id":"AAPS380","score":0.5897,"title":"Fearless First: Negotiating the Hidden Curriculum in Higher Education and Other Societal Institutions","dept":"Academic Achievement Programs"},{"id":"EDHI677","score":0.5818,"title":"Ranking System in Higher Education: How They Work and Why They Matter","dept":"Education Leadership, Higher Ed and International Ed"},{"id":"EDHI662","score":0.5811,"title":"Research on Ethnic Minorities and Demographic Trends in Higher Education","dept":"Education Leadership, Higher Ed and International Ed"}]}