{"course_id":"GEOL682","neighbors":[{"id":"ENFP426","score":0.8689,"title":"Computational Methods in Fire Protection","dept":"Engineering, Fire Protection"},{"id":"PHYS474","score":0.8395,"title":"Computational Physics","dept":"Physics"},{"id":"CMSC754","score":0.7941,"title":"Computational Geometry","dept":"Computer Science"},{"id":"CMSC423","score":0.7941,"title":"Computational Genomics","dept":"Computer Science"},{"id":"ASTR615","score":0.7941,"title":"Computational Astrophysics","dept":"Astronomy"},{"id":"IMDM327","score":0.7678,"title":"Computational Virtual Reality","dept":"Immersive Media Design"},{"id":"ENAE686","score":0.7254,"title":"Computational and Experimental Methods for Hypersonic Flows","dept":"Engineering, Aerospace"},{"id":"BCHM677","score":0.6666,"title":"Computational Tools in Biochemistry","dept":"Biochemistry"},{"id":"ECON630","score":0.645,"title":"Computational Methods in Macroeconomics","dept":"Economics"},{"id":"NFSC620","score":0.6085,"title":"Diet and Cancer Prevention","dept":"Nutrition and Food Science"}]}