{"course_id":"GVPT409A","neighbors":[{"id":"GVPT409P","score":0.8597,"title":"Seminar in International Relations and World Politics; Conflict in the International System","dept":"Government and Politics"},{"id":"GVPT409J","score":0.8377,"title":"Seminar in International Relations and World Politics; Youth and Conflict","dept":"Government and Politics"},{"id":"GVPT309D","score":0.8327,"title":"Topics in International Relations; Dynamics of Conflict and Conflict Resolution","dept":"Government and Politics"},{"id":"GVPT411","score":0.815,"title":"Conflict in the International System","dept":"Government and Politics"},{"id":"HNUH228A","score":0.769,"title":"Peace in our time? Conflict and Conflict Resolution in International Politics","dept":"University Honors"},{"id":"COMM425","score":0.7635,"title":"Negotiation and Conflict Management","dept":"Communication"},{"id":"BMSO754","score":0.7326,"title":"Negotiation and Conflict Management","dept":"Online Business MS Programs"},{"id":"GVPT808D","score":0.7159,"title":"Selected Topics in Functional Problems in International Relations; Multi-Track Diplomacy: Transforming Violent Conflict","dept":"Government and Politics"},{"id":"GVPT410","score":0.7128,"title":"Politics of Nationalist and Ethnic Conflict","dept":"Government and Politics"},{"id":"PLCY752","score":0.71,"title":"Managing Differences:Resolving Conflict and Negotiating Agreements","dept":"Public Policy"}]}