{"course_id":"HIST371","neighbors":[{"id":"JWST326","score":0.7505,"title":"Jews and Judaism in Antiquity II: First through Seventh Centuries","dept":"Jewish Studies"},{"id":"NAVY301","score":0.593,"title":"Naval Ship Systems II (Weapons)","dept":"Navy"},{"id":"JWST325","score":0.5859,"title":"Jews and Judaism in Antiquity I: Sixth Century BCE through the First Century CE","dept":"Jewish Studies"},{"id":"HIST370","score":0.5859,"title":"Jews and Judaism in Antiquity I: Sixth Century BCE through the First Century CE","dept":"History"},{"id":"RELS319D","score":0.5804,"title":"Special Topics in Religious Studies; Jews and Judaism in Antiquity II: First through Seventh Century","dept":"Religious Studies"},{"id":"HIST476","score":0.5688,"title":"Jews in Medieval Times 1000-1450","dept":"History"},{"id":"JWST432","score":0.5688,"title":"Jews in Medieval Times 1000-1450","dept":"Jewish Studies"},{"id":"JWST333","score":0.5266,"title":"Martyrs & Merchants, Lawyers & Mystics, Magicians & Messiahs: Jews Between Medieval and Modern Times","dept":"Jewish Studies"},{"id":"HIST373","score":0.5266,"title":"Martyrs & Merchants, Lawyers & Mystics, Magicians & Messiahs: Jews Between Medieval and Modern Times","dept":"History"},{"id":"MUSC491","score":0.5077,"title":"Conducting II","dept":"School of Music"}]}