{"course_id":"HIST307","neighbors":[{"id":"JWST345","score":1.0,"title":"The Holocaust of European Jewry","dept":"Jewish Studies"},{"id":"RELS343","score":1.0,"title":"The European Reformations","dept":"Religious Studies"},{"id":"HIST333","score":1.0,"title":"The European Reformations","dept":"History"},{"id":"CMSC456","score":0.9197,"title":"Cryptography","dept":"Computer Science"},{"id":"GVPT217","score":0.9197,"title":"Mock Trial","dept":"Government and Politics"},{"id":"GERS141","score":0.9197,"title":"Yiddish I","dept":"German Studies"},{"id":"ENEE456","score":0.9197,"title":"Cryptography","dept":"Electrical & Computer Engineering"},{"id":"AASP370","score":0.9197,"title":"Spike Lee's Joints","dept":"African American Studies"},{"id":"HNUH368T","score":0.9197,"title":"U.S. Diplomacy and Policymaking","dept":"University Honors"},{"id":"CINE353","score":0.9197,"title":"Spike Lee's Joints","dept":"Cinema and Media Studies"}]}