{"course_id":"HIST408C","neighbors":[{"id":"RELS319I","score":0.5031,"title":"Special Topics in Religious Studies; Women in the Qur'an","dept":"Religious Studies"},{"id":"EDCI698","score":0.4829,"title":"Conducting Research on Teaching","dept":"Curriculum and Instruction"},{"id":"GBHL389","score":0.4811,"title":"Global Health Research","dept":"Global Health"},{"id":"MIEH788","score":0.4685,"title":"Critical Readings in Environmental Health","dept":"Maryland Institute for Applied Environmental Health"},{"id":"ENTS689K","score":0.4598,"title":"Special Topics in Telecommunications; Telecommunications Entrepreneurial Practicum","dept":"Telecommunications"},{"id":"CMSC801","score":0.4576,"title":"Department Internal Research Seminar","dept":"Computer Science"},{"id":"HIST408W","score":0.4519,"title":"Senior Seminar; Cultural Memory in Early Islam","dept":"History"},{"id":"MUSC329B","score":0.4519,"title":"Ensemble; Chamber Singers","dept":"School of Music"},{"id":"MUSC629A","score":0.4519,"title":"Ensemble; Symphony Orchestra","dept":"School of Music"},{"id":"MUSC229Z","score":0.4519,"title":"Ensemble; Jazz Combo","dept":"School of Music"}]}