{"course_id":"HIST395","neighbors":[{"id":"HONR100","score":1.0,"title":"Honors Colloquium","dept":"Honors"},{"id":"GEMS100","score":0.8794,"title":"Freshman Honors Colloquium: Introduction to Gemstone","dept":"Gemstone"},{"id":"HIST396","score":0.8404,"title":"Honors Colloquium II","dept":"History"},{"id":"GEOL488","score":0.7847,"title":"Geology Colloquium; Geology Colloquium","dept":"Geology"},{"id":"GEOL688","score":0.7847,"title":"Geology Colloquium; Geology Colloquium","dept":"Geology"},{"id":"ENTM788C","score":0.7452,"title":"Entomological Topics; Colloquium","dept":"Entomology"},{"id":"ENGL370","score":0.6755,"title":"Junior Honors Conference","dept":"English"},{"id":"HONR349I","score":0.6648,"title":"Honors Colloquium; Leading and Investing in Social Change: Redefining and Experimenting with Philanthropy","dept":"Honors"},{"id":"CMSC390","score":0.6507,"title":"Honors Paper","dept":"Computer Science"},{"id":"HONR349B","score":0.6114,"title":"Honors Colloquium; Australian Literature and Culture","dept":"Honors"}]}