{"course_id":"HIST608G","neighbors":[{"id":"GEOG423","score":0.719,"title":"Latin America","dept":"Geographical Sciences"},{"id":"SPAN442","score":0.7009,"title":"Detective Fiction in Latin America","dept":"Spanish"},{"id":"PORT388G","score":0.6848,"title":"Special Topics in Brazilian Studies; Graphic Novels: Discussing Latin America","dept":"Portuguese"},{"id":"HIST251","score":0.6772,"title":"Latin America Since Independence","dept":"History"},{"id":"LACS251","score":0.6772,"title":"Latin America Since Independence","dept":"Latin American and Caribbean Studies"},{"id":"LASC251","score":0.6772,"title":"Latin America Since Independence","dept":"Certificate in Latin American Studies"},{"id":"THET408X","score":0.6757,"title":"Seminar: Theory and Performance Studies; Performing Latin(x) America","dept":"Theatre"},{"id":"LASC250","score":0.6662,"title":"History of Colonial Latin America","dept":"Certificate in Latin American Studies"},{"id":"LACS250","score":0.6662,"title":"History of Colonial Latin America","dept":"Latin American and Caribbean Studies"},{"id":"HIST250","score":0.6662,"title":"History of Colonial Latin America","dept":"History"}]}