{"course_id":"HLSA484","neighbors":[{"id":"HLSA732","score":0.8382,"title":"The Evolving U.S. Health Care System","dept":"Health Services Administration"},{"id":"HLTH498J","score":0.7201,"title":"Special Topics in Health; Health Inequality","dept":"Health"},{"id":"HLTH688J","score":0.716,"title":"Special Problems in Health Education; Health Inequality","dept":"Health"},{"id":"HLTH780","score":0.7126,"title":"Community Health","dept":"Health"},{"id":"WGSS428J","score":0.6983,"title":"Topics in Women, Gender, and Sexuality Studies; Health Inequality","dept":"Women, Gender, and Sexuality Studies"},{"id":"WGSS698J","score":0.6975,"title":"Special Topics in Women, Gender, and Sexuality Studies; Health Inequality","dept":"Women, Gender, and Sexuality Studies"},{"id":"HLSA770","score":0.6933,"title":"Continuous Quality Improvement in Healthcare","dept":"Health Services Administration"},{"id":"HLSA747","score":0.6864,"title":"Health Care Management Research","dept":"Health Services Administration"},{"id":"HLTH306H","score":0.6477,"title":"Macro Level Influences on Community Health","dept":"Health"},{"id":"HLTH306","score":0.6477,"title":"Macro Level Influences on Community Health","dept":"Health"}]}