{"course_id":"HNUH218X","neighbors":[{"id":"CCJS346","score":0.8645,"title":"Domestic Violence","dept":"Criminology and Criminal Justice"},{"id":"PSYC381","score":0.8318,"title":"Community Interventions: Domestic Violence I","dept":"Psychology"},{"id":"FMSC460","score":0.776,"title":"Violence in Families","dept":"Family Science"},{"id":"PSYC318D","score":0.7702,"title":"Community Interventions: Domestic Violence I; Community Interventions: Domestic Violence","dept":"Psychology"},{"id":"CCJS225","score":0.7583,"title":"Responses to Violence","dept":"Criminology and Criminal Justice"},{"id":"ANSC204","score":0.7299,"title":"Anatomy of Domestic Animals","dept":"Animal Science"},{"id":"EDHD221","score":0.7027,"title":"Aggression and Violence in Everyday Life: Can Violence Be Prevented?","dept":"Education, Human Development"},{"id":"AASP499U","score":0.691,"title":"Advanced Topics in Public Policy and the Black Community; End Gun Violence: An Analysis of Structural Violence, Interpersonal Violence and Trauma in African-American Communities","dept":"African American Studies"},{"id":"ANTH385","score":0.6688,"title":"End Gun Violence: An Analysis of Structural Violence, Interpersonal Violence and Trauma in African-American Communities","dept":"Anthropology"},{"id":"AAAS485","score":0.6688,"title":"End Gun Violence: An Analysis of Structural Violence, Interpersonal Violence and Trauma in African-American Communities","dept":"African American and Africana Studies"}]}