{"course_id":"HONR299G","neighbors":[{"id":"HONR219M","score":0.7504,"title":"Honors Seminar; Why Do We Do What We Do? The Role of Motivation in People's Achievements and Choices","dept":"Honors"},{"id":"HONR298W","score":0.7426,"title":"Honors Seminar; Political Disagreement and the Limits of Toleration","dept":"Honors"},{"id":"HIST226","score":0.707,"title":"Revolution, Regret, and Reform: The People and Principles in American Political History","dept":"History"},{"id":"HONR218T","score":0.6773,"title":"Honors Seminar; Political Theater: On Stage and in Washington","dept":"Honors"},{"id":"HONR288P","score":0.6666,"title":"Honors Seminar; Why Do Things Burn?","dept":"Honors"},{"id":"HONR288O","score":0.6666,"title":"Honors Seminar: Why Do Things Fail?","dept":"Honors"},{"id":"HONR289P","score":0.6612,"title":"Honors Seminar; How Do Innovators Think?","dept":"Honors"},{"id":"HONR209X","score":0.6588,"title":"Honors Seminar; Karl Marx: Dead or Alive?","dept":"Honors"},{"id":"HONR239K","score":0.6588,"title":"Honors Seminar; The Multicultural Metropolis","dept":"Honors"},{"id":"HONR208P","score":0.6588,"title":"Honors Seminar; Tolkien: Mythmaker","dept":"Honors"}]}