{"course_id":"IDEA498","neighbors":[{"id":"IDEA698","score":0.8838,"title":"Independent Study in Design Thinking","dept":"Academy for Innovation & Entrepreneurship"},{"id":"EDUC770","score":0.48,"title":"System Innovation and Transformation","dept":"Education"},{"id":"BMGT352","score":0.48,"title":"Customer-Centric Innovation","dept":"Business and Management"},{"id":"BMGT456","score":0.48,"title":"Customer-Centric Innovation","dept":"Business and Management"},{"id":"IDEA258D","score":0.4699,"title":"Special Topics in Innovation; Explorations in Design","dept":"Academy for Innovation & Entrepreneurship"},{"id":"MAIT699","score":0.4663,"title":"Independent Masters Project","dept":"Masters in the Mathematics of Advanced Industrial Tech"},{"id":"HEIP240","score":0.4538,"title":"Exploring International Entrepreneurship and Innovation","dept":"Entrepreneurship and Innovation"},{"id":"ENES464","score":0.4513,"title":"International Entrepreneurship and Innovation","dept":"Engineering Science"},{"id":"BUSI793","score":0.4512,"title":"Technology Entrepreneurship, Innovation and Commercialization","dept":"Part-Time MBA Program"},{"id":"SMLP472","score":0.441,"title":"Strategies for Innovation & Entrepreneurship","dept":"Southern Management Leadership Program"}]}