{"course_id":"JAPN302","neighbors":[{"id":"JAPN301","score":0.8419,"title":"Advanced Japanese I","dept":"Japanese"},{"id":"JAPN404","score":0.8419,"title":"Advanced Japanese Through Manga","dept":"Japanese"},{"id":"JAPN202","score":0.7288,"title":"Intermediate Japanese II","dept":"Japanese"},{"id":"JAPN107","score":0.7256,"title":"Elementary Japanese II","dept":"Japanese"},{"id":"JAPN102","score":0.7256,"title":"Elementary Japanese II","dept":"Japanese"},{"id":"ECON702","score":0.688,"title":"Advanced Macroeconomics II","dept":"Economics"},{"id":"ECON704","score":0.688,"title":"Advanced Microeconomics II","dept":"Economics"},{"id":"MATH411","score":0.688,"title":"Advanced Calculus II","dept":"Mathematics"},{"id":"JAPN398D","score":0.67,"title":"Special Topics in Japanese Linguistics; The Sounds and Dialects of Japanese","dept":"Japanese"},{"id":"MUSC629L","score":0.6226,"title":"Ensemble; Advanced Japanese Koto","dept":"School of Music"}]}