{"course_id":"LBSC706","neighbors":[{"id":"INST301","score":0.6378,"title":"Introduction to Information Science","dept":"Information Studies"},{"id":"INST201","score":0.6378,"title":"Introduction to Information Science","dept":"Information Studies"},{"id":"LBSC708K","score":0.6245,"title":"Special Topics in Library and Information Science; Carceral Librarianship","dept":"Library Science"},{"id":"LBSC708U","score":0.6245,"title":"Special Topics in Library and Information Science; Outreach, Inclusion, and Crowdsourcing","dept":"Library Science"},{"id":"LBSC708X","score":0.6227,"title":"Special Topics in Library and Information Science; Roles and Responses during Crises","dept":"Library Science"},{"id":"INST408O","score":0.6214,"title":"Special Topics in Information Science; Project Management for Information Science","dept":"Information Studies"},{"id":"INST408G","score":0.616,"title":"Special Topics in Information Science; Do You Like Research?: Exploring Research in Information Science","dept":"Information Studies"},{"id":"INST326","score":0.5936,"title":"Object-Oriented Programming for Information Science","dept":"Information Studies"},{"id":"INST408U","score":0.5913,"title":"Special Topics in Information Science; Information Assurance and Compliance","dept":"Information Studies"},{"id":"INST347","score":0.5855,"title":"Cloud Computing for Information Science","dept":"Information Studies"}]}