{"course_id":"MATH868C","neighbors":[{"id":"MATH660","score":0.9522,"title":"Complex Analysis I","dept":"Mathematics"},{"id":"MATH868A","score":0.9522,"title":"SelectedTopics in Complex Analysis","dept":"Mathematics"},{"id":"MATH463","score":0.904,"title":"Complex Variables","dept":"Mathematics"},{"id":"SURV742","score":0.904,"title":"Inference from Complex Surveys","dept":"Survey and Data Science"},{"id":"MATH868B","score":0.8488,"title":"SelectedTopics in Complex Analysis; Selected Topics in Complex Variables","dept":"Mathematics"},{"id":"SURV701","score":0.7892,"title":"Analysis of Complex Sample Data","dept":"Survey and Data Science"},{"id":"MATH661","score":0.7542,"title":"Complex Analysis II","dept":"Mathematics"},{"id":"SURV702","score":0.6537,"title":"Analysis of Complex Survey Data","dept":"Survey and Data Science"},{"id":"MATH868F","score":0.6302,"title":"SelectedTopics in Complex Analysis; Introduction to Teichueller Dynamics","dept":"Mathematics"},{"id":"SURV699N","score":0.5516,"title":"Special Topics in Survey Methodology; Analysis of Complex Samples for Population Inference","dept":"Survey Methodology"}]}