{"course_id":"MSAI633","neighbors":[{"id":"PHIL209M","score":0.554,"title":"Philosophical Issues; AI and the Human Experience","dept":"Philosophy"},{"id":"PHPE308N","score":0.5513,"title":"Special Topics in Philosophy, Politics, and Economics; AI and the Human Experience","dept":"Philosophy, Politics, and Economics"},{"id":"BOIS602","score":0.5092,"title":"AI Augmented Database Management","dept":"Online MS Info Systems and Artificial Intelligence"},{"id":"BUDT702","score":0.5092,"title":"AI Augmented Database Management","dept":"Decision and Information Technologies"},{"id":"CMSC116","score":0.4963,"title":"You and I, and Generative AI","dept":"Computer Science"},{"id":"IMDM498E","score":0.4924,"title":"Special Topics in Immersive Media; Creative Experiments with AI","dept":"Immersive Media Design"},{"id":"ENPM808Y","score":0.4804,"title":"Advanced Topics in Engineering; Fundamental Concepts of AI and Machine Learning, and Their Applications","dept":"Engineering, Professional Masters"},{"id":"HNUH248R","score":0.4705,"title":"Artificial Intelligence: Critical Examinations through Science Fiction and Technology","dept":"University Honors"},{"id":"ARTT489E","score":0.4606,"title":"Advanced Special Topics in Art; Creative Experiments with AI","dept":"Art Studio"},{"id":"MSAI630","score":0.4573,"title":"Safe and Trustworthy AI","dept":"Master of Science in Artificial Intelligence"}]}