{"course_id":"MUED698T","neighbors":[{"id":"MUED698L","score":0.9061,"title":"Current Trends in Music Education; Teaching, Learning, and Music","dept":"Music Education"},{"id":"MUED499T","score":0.8048,"title":"Workshops, Clinics, Institutes; Teaching Music with Technology","dept":"Music Education"},{"id":"MUED698C","score":0.8027,"title":"Current Trends in Music Education; Cultural Competency in the Music Classroom","dept":"Music Education"},{"id":"MUED499M","score":0.7907,"title":"Workshops, Clinics, Institutes; Motivation in Music and Music Teaching","dept":"Music Education"},{"id":"MUED342","score":0.7888,"title":"Technology for Music Education","dept":"Music Education"},{"id":"MUED698Q","score":0.7763,"title":"Current Trends in Music Education; Qualitative and Mixed Methods Research in Music Education","dept":"Music Education"},{"id":"MUED433","score":0.7472,"title":"Teaching Choral Music","dept":"Music Education"},{"id":"MUED472","score":0.7472,"title":"Teaching Choral Music","dept":"Music Education"},{"id":"MUED698G","score":0.7399,"title":"Current Trends in Music Education; Gordon Institute for Music Learning Professional Development Levels","dept":"Music Education"},{"id":"MUED698M","score":0.7139,"title":"Current Trends in Music Education; Comprehensive Musicianship through Performance in Ensembles","dept":"Music Education"}]}