{"course_id":"PERS298A","neighbors":[{"id":"FILM298M","score":0.9762,"title":"Special Topics in International Film Studies; Digital Art and Media in Iran and Its Diaspora","dept":"Film Studies"},{"id":"COMM365","score":0.6271,"title":"Social Media & Digital Culture","dept":"Communication"},{"id":"HLTH264","score":0.5775,"title":"Digital Health & Social Media","dept":"Health"},{"id":"HLTH264H","score":0.5775,"title":"Tweets & Likes: Digital Health & Social Media","dept":"Health"},{"id":"COMM449N","score":0.5733,"title":"Special Topics in Digital Communication; Influencer Culture","dept":"Communication"},{"id":"INST151","score":0.5553,"title":"Becoming A Social Media Influencer","dept":"Information Studies"},{"id":"COMM449B","score":0.5493,"title":"Special Topics in Digital Communication; Communication and Social Media","dept":"Communication"},{"id":"COMM363","score":0.5444,"title":"Developing Digital Media: Blogs, Magazines, and their Audiences","dept":"Communication"},{"id":"ARTT479E","score":0.5351,"title":"Advanced Digital Media Studio; Art and Electronics","dept":"Art Studio"},{"id":"COMM449H","score":0.5237,"title":"Special Topics in Digital Communication; Digital Placemaking","dept":"Communication"}]}