{"course_id":"SURV772","neighbors":[{"id":"ENCE689W","score":0.7312,"title":"Seminar; Design of Mass Timber","dept":"Engineering, Civil"},{"id":"SURV699E","score":0.7282,"title":"Special Topics in Survey Methodology; Survey Design and Implementation in International Contexts","dept":"Survey Methodology"},{"id":"MUSC445","score":0.6834,"title":"Survey of the Opera","dept":"School of Music"},{"id":"JOUR199","score":0.6834,"title":"Survey Apprenticeship","dept":"Journalism"},{"id":"SURV744","score":0.6431,"title":"Topics in Survey Methodology","dept":"Survey Methodology"},{"id":"URSP805","score":0.6135,"title":"Seminar in Research Design","dept":"Urban Studies and Planning"},{"id":"SURV699","score":0.6031,"title":"Special Topics in Survey Methodology; Readings in Survey Methodology","dept":"Survey and Data Science"},{"id":"SURV699S","score":0.5932,"title":"Special Topics in Survey Methodology; Web Survey Methodology","dept":"Survey Methodology"},{"id":"SURV699V","score":0.5932,"title":"Special Topics in Survey Methodology; Web Survey Methodology","dept":"Survey Methodology"},{"id":"SDSB340","score":0.5875,"title":"Introduction to Survey Methodology","dept":"Social Data Science, BSOS"}]}