{"course_id":"WGSS422","neighbors":[{"id":"AAST422","score":1.0,"title":"Asian American Women and Gender","dept":"Asian American Studies"},{"id":"AAST498G","score":0.839,"title":"Advanced Topics in Asian American Studies; Asian American Women and Gender","dept":"Asian American Studies"},{"id":"AAST201","score":0.7885,"title":"Asian American History","dept":"Asian American Studies"},{"id":"HIST221","score":0.7885,"title":"Asian American History","dept":"History"},{"id":"AMST498J","score":0.7706,"title":"Asian American Politics","dept":"American Studies"},{"id":"AAST443","score":0.7706,"title":"Asian American Politics","dept":"Asian American Studies"},{"id":"GVPT368C","score":0.7706,"title":"Asian American Politics","dept":"Government and Politics"},{"id":"WGSS498I","score":0.7628,"title":"Advanced Special Topics in Women, Gender, and Sexuality Studies; Asian American Women and Gender","dept":"Women, Gender, and Sexuality Studies"},{"id":"PSYC262","score":0.7466,"title":"Asian American Psychology","dept":"Psychology"},{"id":"AAST262","score":0.7466,"title":"Asian American Psychology","dept":"Asian American Studies"}]}